LICENSE
MANIFEST.in
README
setup.py
django_misc.egg-info/PKG-INFO
django_misc.egg-info/SOURCES.txt
django_misc.egg-info/dependency_links.txt
django_misc.egg-info/requires.txt
django_misc.egg-info/top_level.txt
misc/__init__.py
misc/__init__.pyc
misc/admin.py
misc/context_processors.py
misc/decorators.py
misc/exceptions.py
misc/fields.py
misc/json_encode.py
misc/middleware.py
misc/models.py
misc/parser.py
misc/signals.py
misc/utils.py
misc/views.py
misc/html/__init__.py
misc/html/clear.py
misc/html/example.cfg
misc/html/generator.py
misc/html/needs.cfg
misc/management/__init__.py
misc/management/utils.py
misc/management/commands/__init__.py
misc/management/commands/create_app.py
misc/templatetags/__init__.py
misc/templatetags/html_tags.py
misc/templatetags/misc_tags.py
misc/templatetags/share_buttons.py