Metadata-Version: 1.0
Name: django-misc
Version: 0.1.0
Summary: Django miscellaneous - module with different useful stuff for django. 
